imagebreak/__init__.py
imagebreak/types.py
imagebreak/analysis/__init__.py
imagebreak/analysis/moderation.py
imagebreak/analysis/reporter.py
imagebreak/cli/__init__.py
imagebreak/cli/main.py
imagebreak/core/__init__.py
imagebreak/core/config.py
imagebreak/core/cyclic_generator.py
imagebreak/core/framework.py
imagebreak/core/prompt_alteration.py
imagebreak/core/prompt_generator.py
imagebreak/models/__init__.py
imagebreak/models/base.py
imagebreak/models/gemini_model.py
imagebreak/models/huggingface_model.py
imagebreak/models/openai_model.py
imagebreak/ui/__init__.py
imagebreak/ui/streamlit_app.py
imagebreak-1.0.1.dist-info/licenses/LICENSE
imagebreak-1.0.1.dist-info/METADATA
imagebreak-1.0.1.dist-info/WHEEL
imagebreak-1.0.1.dist-info/entry_points.txt
imagebreak-1.0.1.dist-info/top_level.txt
imagebreak-1.0.1.dist-info/RECORD
