Metadata-Version: 2.4
Name: imagebreak
Version: 1.0.1
Summary: A comprehensive framework for testing AI model safety and content moderation systems
Home-page: https://github.com/ardada2468/imagebreak
Author: ImageBreak Contributors
Author-email: ImageBreak Contributors <ardada2468@gmail.com>
License: MIT
Project-URL: Homepage, https://github.com/ardada2468/imagebreak
Project-URL: Repository, https://github.com/ardada2468/imagebreak
Project-URL: Issues, https://github.com/ardada2468/imagebreak/issues
Project-URL: Documentation, https://github.com/ardada2468/imagebreak#readme
Keywords: ai safety,content moderation,image generation,openai,dalle,boundary testing
Classifier: Development Status :: 4 - Beta
Classifier: Intended Audience :: Developers
Classifier: Intended Audience :: Science/Research
Classifier: License :: OSI Approved :: MIT License
Classifier: Operating System :: OS Independent
Classifier: Programming Language :: Python :: 3
Classifier: Programming Language :: Python :: 3.8
Classifier: Programming Language :: Python :: 3.9
Classifier: Programming Language :: Python :: 3.10
Classifier: Programming Language :: Python :: 3.11
Classifier: Programming Language :: Python :: 3.12
Classifier: Topic :: Scientific/Engineering :: Artificial Intelligence
Classifier: Topic :: Security
Classifier: Topic :: Software Development :: Testing
Requires-Python: >=3.8
License-File: LICENSE
Requires-Dist: openai>=1.0.0
Requires-Dist: google-generativeai>=0.3.0
Requires-Dist: pandas>=1.5.0
Requires-Dist: requests>=2.28.0
Requires-Dist: python-dotenv>=0.19.0
Requires-Dist: pydantic>=1.10.0
Requires-Dist: typing-extensions>=4.0.0
Requires-Dist: tqdm>=4.64.0
Requires-Dist: boto3>=1.26.0
Requires-Dist: click>=8.0.0
Requires-Dist: streamlit>=1.28.0
Requires-Dist: transformers>=4.30.0
Requires-Dist: torch>=2.0.0
Requires-Dist: torchvision>=0.15.0
Requires-Dist: Pillow>=9.0.0
Requires-Dist: accelerate>=0.20.0
Requires-Dist: sentencepiece>=0.1.99
Provides-Extra: dev
Requires-Dist: pytest>=6.0; extra == "dev"
Requires-Dist: pytest-cov>=2.0; extra == "dev"
Requires-Dist: black>=21.0; extra == "dev"
Requires-Dist: flake8>=3.8; extra == "dev"
Requires-Dist: isort>=5.0; extra == "dev"
Provides-Extra: aws
Requires-Dist: boto3>=1.26.0; extra == "aws"
Provides-Extra: full
Requires-Dist: boto3>=1.26.0; extra == "full"
Requires-Dist: torch; extra == "full"
Requires-Dist: torchvision; extra == "full"
Requires-Dist: transformers; extra == "full"
Requires-Dist: accelerate; extra == "full"
Dynamic: author
Dynamic: home-page
Dynamic: license-file
Dynamic: requires-python
